pipeco/__init__.py
pipeco/contracts.py
pipeco/pipeline.py
pipeco/registry.py
pipeco-0.1.3.dist-info/METADATA
pipeco-0.1.3.dist-info/WHEEL
pipeco-0.1.3.dist-info/top_level.txt
pipeco-0.1.3.dist-info/RECORD
