Metadata-Version: 2.4
Name: pipeco
Version: 0.1.3
Summary: An easy-to-use pipeline builder.
Author-email: "Austin E. Y. T. Lefebvre" <austin.e.lefebvre@gmail.com>
Project-URL: Homepage, https://github.com/aelefebv/pipeco
Project-URL: Issues, https://github.com/aelefebv/pipeco/issues
Requires-Python: >=3.11
Requires-Dist: pydantic>=2.12.4
